podcast_tts/__init__.py
podcast_tts/podcast_tts.py
podcast_tts-0.0.1.dist-info/LICENSE
podcast_tts-0.0.1.dist-info/METADATA
podcast_tts-0.0.1.dist-info/WHEEL
podcast_tts-0.0.1.dist-info/top_level.txt
podcast_tts-0.0.1.dist-info/RECORD
