Metadata-Version: 2.1
Name: podcast_tts
Version: 0.0.1
Summary: Generate high-quality TTS audio for podcasts and dialogues.
Home-page: https://github.com/puntorigen/podcast_tts
Author: Pablo Schaffner
Author-email: pablo@puntorigen.com
Classifier: Programming Language :: Python :: 3
Classifier: License :: OSI Approved :: MIT License
Classifier: Operating System :: OS Independent
Requires-Python: >=3.8
License-File: LICENSE
Requires-Dist: torch
Requires-Dist: torchaudio
Requires-Dist: ChatTTS
Requires-Dist: inflect
Requires-Dist: pydub
Requires-Dist: regex
